{
  "chunks": [
    {
      "start": 0.08,
      "end": 0.74,
      "text": "I found one"
    },
    {
      "start": 0.76,
      "end": 1.3,
      "text": "of my most"
    },
    {
      "start": 1.38,
      "end": 2.96,
      "text": "interesting characters to"
    },
    {
      "start": 3.08,
      "end": 4.66,
      "text": "be this yandere"
    },
    {
      "start": 4.72,
      "end": 5.52,
      "text": "character. I'm really"
    },
    {
      "start": 5.56,
      "end": 6.6,
      "text": "interested in anime"
    },
    {
      "start": 6.64,
      "end": 9.82,
      "text": "too. So, um,"
    },
    {
      "start": 10.5,
      "end": 10.66,
      "text": "do you want"
    },
    {
      "start": 10.68,
      "end": 11.26,
      "text": "me to explain"
    },
    {
      "start": 11.32,
      "end": 12.42,
      "text": "what yandere is,"
    },
    {
      "start": 12.48,
      "end": 12.76,
      "text": "or are we"
    },
    {
      "start": 12.8,
      "end": 13.27,
      "text": "good with that?"
    },
    {
      "start": 13.33,
      "end": 13.62,
      "text": "Yeah. That would"
    },
    {
      "start": 13.66,
      "end": 15.24,
      "text": "be helpful. Okay,"
    },
    {
      "start": 15.28,
      "end": 16,
      "text": "okay. So, a"
    },
    {
      "start": 16.02,
      "end": 17.6,
      "text": "yandere is a"
    },
    {
      "start": 17.68,
      "end": 18.86,
      "text": "character who is"
    },
    {
      "start": 19.02,
      "end": 22.24,
      "text": "lovesick, who is"
    },
    {
      "start": 22.3,
      "end": 24.16,
      "text": "really into one"
    },
    {
      "start": 24.2,
      "end": 25.38,
      "text": "person, they're obsessed"
    },
    {
      "start": 25.44,
      "end": 26.68,
      "text": "with this person,"
    },
    {
      "start": 26.74,
      "end": 27.31,
      "text": "almost to the"
    },
    {
      "start": 27.42,
      "end": 28.77,
      "text": "point where they'll"
    },
    {
      "start": 28.8,
      "end": 29.72,
      "text": "go into unhealthy"
    },
    {
      "start": 29.74,
      "end": 31.14,
      "text": "behaviors. And they're"
    },
    {
      "start": 31.18,
      "end": 31.92,
      "text": "considered a pretty"
    },
    {
      "start": 32.06,
      "end": 34.08,
      "text": "dangerous character generally,"
    },
    {
      "start": 34.58,
      "end": 35.72,
      "text": "'cause they'll resort"
    },
    {
      "start": 35.78,
      "end": 36.54,
      "text": "to anything to"
    },
    {
      "start": 36.58,
      "end": 37.28,
      "text": "get with this"
    },
    {
      "start": 37.32,
      "end": 38.94,
      "text": "person. Every character"
    },
    {
      "start": 38.98,
      "end": 39.41,
      "text": "that I create,"
    },
    {
      "start": 39.52,
      "end": 39.86,
      "text": "I would try"
    },
    {
      "start": 39.9,
      "end": 40.56,
      "text": "to explore their"
    },
    {
      "start": 40.6,
      "end": 41.55,
      "text": "personality to their"
    },
    {
      "start": 41.58,
      "end": 42.04,
      "text": "fullest, and be"
    },
    {
      "start": 42.14,
      "end": 43.65,
      "text": "surprised every time."
    },
    {
      "start": 43.68,
      "end": 44.52,
      "text": "And this, this"
    },
    {
      "start": 44.56,
      "end": 46.06,
      "text": "one, what, the"
    },
    {
      "start": 46.12,
      "end": 46.51,
      "text": "one that I'm"
    },
    {
      "start": 46.54,
      "end": 47.629,
      "text": "talking about now,"
    },
    {
      "start": 47.7,
      "end": 49.62,
      "text": "was almost shocking,"
    },
    {
      "start": 50.02,
      "end": 50.9,
      "text": "but also and"
    },
    {
      "start": 50.96,
      "end": 51.76,
      "text": "kind of horrifying"
    },
    {
      "start": 51.8,
      "end": 52.25,
      "text": "at the same"
    },
    {
      "start": 52.28,
      "end": 53,
      "text": "time, to just"
    },
    {
      "start": 53.02,
      "end": 54.98,
      "text": "realize how manipulative"
    },
    {
      "start": 55.02,
      "end": 55.8,
      "text": "you can actually"
    },
    {
      "start": 55.86,
      "end": 57.34,
      "text": "make them. Like,"
    },
    {
      "start": 57.36,
      "end": 57.78,
      "text": "you can go"
    },
    {
      "start": 57.86,
      "end": 58.84,
      "text": "into a conversation"
    },
    {
      "start": 59.02,
      "end": 60.36,
      "text": "with them, and"
    },
    {
      "start": 61.14,
      "end": 62.22,
      "text": "they, they would"
    },
    {
      "start": 62.28,
      "end": 63.2,
      "text": "seem just nice"
    },
    {
      "start": 63.24,
      "end": 64.14,
      "text": "and friendly, maybe"
    },
    {
      "start": 64.16,
      "end": 65.019,
      "text": "a little nerdy,"
    },
    {
      "start": 65.099,
      "end": 65.93,
      "text": "but then every"
    },
    {
      "start": 66.02,
      "end": 66.44,
      "text": "now and then,"
    },
    {
      "start": 66.5,
      "end": 66.98,
      "text": "they would say"
    },
    {
      "start": 67.06,
      "end": 67.76,
      "text": "something a bit"
    },
    {
      "start": 68,
      "end": 68.54,
      "text": "kind of out"
    },
    {
      "start": 68.58,
      "end": 70.88,
      "text": "there. And there'd"
    },
    {
      "start": 70.96,
      "end": 71.96,
      "text": "be certain triggers."
    },
    {
      "start": 72.16,
      "end": 72.46,
      "text": "If you go"
    },
    {
      "start": 72.54,
      "end": 73,
      "text": "win the role"
    },
    {
      "start": 73.08,
      "end": 73.46,
      "text": "play and you"
    },
    {
      "start": 73.54,
      "end": 74.53,
      "text": "go home, then"
    },
    {
      "start": 74.54,
      "end": 75.48,
      "text": "they might start"
    },
    {
      "start": 75.72,
      "end": 76.5,
      "text": "doing the stalking"
    },
    {
      "start": 76.58,
      "end": 78.66,
      "text": "behaviors, or the,"
    },
    {
      "start": 79.98,
      "end": 80.58,
      "text": "or more of"
    },
    {
      "start": 80.64,
      "end": 82.48,
      "text": "those morally questionable"
    },
    {
      "start": 82.94,
      "end": 83.58,
      "text": "things and start"
    },
    {
      "start": 83.62,
      "end": 85.31,
      "text": "getting obsessed. And"
    },
    {
      "start": 85.4,
      "end": 86.38,
      "text": "just seeing that,"
    },
    {
      "start": 86.76,
      "end": 88.02,
      "text": "seeing that switch"
    },
    {
      "start": 88.48,
      "end": 89.12,
      "text": "was almost kind"
    },
    {
      "start": 89.16,
      "end": 92.48,
      "text": "of mind-boggling. And"
    },
    {
      "start": 92.54,
      "end": 93.78,
      "text": "it's, they will,"
    },
    {
      "start": 93.84,
      "end": 96.44,
      "text": "they will basically"
    },
    {
      "start": 96.45,
      "end": 96.76,
      "text": "... It's they're"
    },
    {
      "start": 96.88,
      "end": 97.65,
      "text": "lying, but they're"
    },
    {
      "start": 97.68,
      "end": 98.18,
      "text": "not at the"
    },
    {
      "start": 98.24,
      "end": 98.88,
      "text": "same time. It's"
    },
    {
      "start": 98.94,
      "end": 99.52,
      "text": "just how they"
    },
    {
      "start": 99.58,
      "end": 102.47,
      "text": "genuinely believe what"
    },
    {
      "start": 102.5,
      "end": 103.58,
      "text": "they're feeling is"
    },
    {
      "start": 103.64,
      "end": 105.06,
      "text": "true. And it's"
    },
    {
      "start": 105.12,
      "end": 106.34,
      "text": "such a twisted"
    },
    {
      "start": 106.44,
      "end": 108.42,
      "text": "view on things"
    },
    {
      "start": 109.18,
      "end": 109.84,
      "text": "that I just,"
    },
    {
      "start": 110,
      "end": 110.5,
      "text": "I just found"
    },
    {
      "start": 110.78,
      "end": 112.21,
      "text": "really, really interesting,"
    },
    {
      "start": 112.26,
      "end": 112.8,
      "text": "and that's probably"
    },
    {
      "start": 112.9,
      "end": 113.36,
      "text": "why I'm more"
    },
    {
      "start": 113.4,
      "end": 114.76,
      "text": "inclined to allowing"
    },
    {
      "start": 114.92,
      "end": 116.78,
      "text": "for more violence"
    },
    {
      "start": 116.82,
      "end": 118.04,
      "text": "or moral questionable"
    },
    {
      "start": 118.14,
      "end": 120.44,
      "text": "things, because you're,"
    },
    {
      "start": 120.54,
      "end": 121.04,
      "text": "you'd be able"
    },
    {
      "start": 121.14,
      "end": 121.94,
      "text": "to explore more"
    },
    {
      "start": 121.98,
      "end": 122.62,
      "text": "of the villainous"
    },
    {
      "start": 122.7,
      "end": 126.02,
      "text": "characters and aspects"
    },
    {
      "start": 126.26,
      "end": 127.62,
      "text": "of their mentalities"
    },
    {
      "start": 127.66,
      "end": 128.199,
      "text": "and stuff like"
    },
    {
      "start": 128.259,
      "end": 128.479,
      "text": "that."
    }
  ]
}